openworld/sdk/testsdk/client/order_purchase_screen_client.py
openworld/sdk/testsdk/client/order_purchase_update_client.py
openworld/sdk/testsdk/model/address.py
openworld/sdk/testsdk/model/air.py
openworld/sdk/testsdk/model/air_segment.py
openworld/sdk/testsdk/model/amount.py
openworld/sdk/testsdk/model/authorize.py
openworld/sdk/testsdk/model/authorize_reversal.py
openworld/sdk/testsdk/model/cancellation_reason.py
openworld/sdk/testsdk/model/capture.py
openworld/sdk/testsdk/model/car.py
openworld/sdk/testsdk/model/chargeback_detail.py
openworld/sdk/testsdk/model/chargeback_feedback.py
openworld/sdk/testsdk/model/credit_card.py
openworld/sdk/testsdk/model/cruise.py
openworld/sdk/testsdk/model/customer_account.py
openworld/sdk/testsdk/model/device_details.py
openworld/sdk/testsdk/model/email.py
openworld/sdk/testsdk/model/error.py
openworld/sdk/testsdk/model/error_cause.py
openworld/sdk/testsdk/model/error_detail.py
openworld/sdk/testsdk/model/extended_error.py
openworld/sdk/testsdk/model/fraud_decision.py
openworld/sdk/testsdk/model/hotel.py
openworld/sdk/testsdk/model/insult_detail.py
openworld/sdk/testsdk/model/insult_feedback.py
openworld/sdk/testsdk/model/insurance.py
openworld/sdk/testsdk/model/name.py
openworld/sdk/testsdk/model/operations.py
openworld/sdk/testsdk/model/order_purchase_screen_request.py
openworld/sdk/testsdk/model/order_purchase_screen_response.py
openworld/sdk/testsdk/model/order_purchase_transaction.py
openworld/sdk/testsdk/model/order_purchase_update_request.py
openworld/sdk/testsdk/model/order_update.py
openworld/sdk/testsdk/model/pay_pal.py
openworld/sdk/testsdk/model/payment.py
openworld/sdk/testsdk/model/payment_method.py
openworld/sdk/testsdk/model/payment_operation.py
openworld/sdk/testsdk/model/payment_outcome.py
openworld/sdk/testsdk/model/payment_reason.py
openworld/sdk/testsdk/model/payment_status.py
openworld/sdk/testsdk/model/payment_three_ds_criteria.py
openworld/sdk/testsdk/model/payment_update.py
openworld_sdk_python_testsdk-0.2.dist-info/METADATA
openworld_sdk_python_testsdk-0.2.dist-info/WHEEL
openworld_sdk_python_testsdk-0.2.dist-info/top_level.txt
openworld_sdk_python_testsdk-0.2.dist-info/RECORD
